gcpm/__init__.py
gcpm/__main__.py
gcpm/__version__.py
gcpm/cli.py
gcpm/condor.py
gcpm/core.py
gcpm/files.py
gcpm/gce.py
gcpm/gcs.py
gcpm/machine.py
gcpm/service.py
gcpm/utils.py
gcpm-0.3.1.dist-info/entry_points.txt
gcpm-0.3.1.dist-info/LICENSE
gcpm-0.3.1.dist-info/WHEEL
gcpm-0.3.1.dist-info/METADATA
gcpm-0.3.1.dist-info/RECORD
