Metadata-Version: 2.1
Name: gcpm
Version: 0.3.1
Summary: Google Cloud Platform Condor Pool Manager
Home-page: https://github.com/rcmdnk/gcpm
License: Apache-2.0
Author: rcmdnk
Author-email: rcmdnk@gmail.com
Requires-Python: >=2.7, !=3.0.*, !=3.1.*, !=3.2.*, !=3.3.*
Classifier: License :: OSI Approved :: Apache Software License
Classifier: Programming Language :: Python :: 2
Classifier: Programming Language :: Python :: 2.7
Classifier: Programming Language :: Python :: 3
Classifier: Programming Language :: Python :: 3.4
Classifier: Programming Language :: Python :: 3.5
Classifier: Programming Language :: Python :: 3.6
Classifier: Programming Language :: Python :: 3.7
Classifier: Programming Language :: Python :: 3.8
Requires-Dist: bandit (>=1.5,<2.0)
Requires-Dist: fire (>=0.1.3,<0.2.0)
Requires-Dist: google-api-python-client (>=1.7,<2.0)
Requires-Dist: google-auth (>=1.6,<2.0)
Requires-Dist: google-auth-httplib2 (>=0.0.3,<0.0.4)
Requires-Dist: htcondor (>=8.9,<9.0)
Requires-Dist: oauth2client (>=4.1,<5.0)
Requires-Dist: ruamel.yaml (>=0.15.83,<0.16.0)
Project-URL: Repository, https://github.com/rcmdnk/gcpm
